vhpc_toolkit/__init__.py
vhpc_toolkit/cluster.py
vhpc_toolkit/command.py
vhpc_toolkit/config_objs.py
vhpc_toolkit/connect.py
vhpc_toolkit/get_args.py
vhpc_toolkit/get_objs.py
vhpc_toolkit/log.py
vhpc_toolkit/operations.py
vhpc_toolkit/version.py
vhpc_toolkit/view.py
vhpc_toolkit/wait.py
vhpc_toolkit-1.0.3.dist-info/METADATA
vhpc_toolkit-1.0.3.dist-info/WHEEL
vhpc_toolkit-1.0.3.dist-info/licenses/LICENSE.txt
vhpc_toolkit-1.0.3.dist-info/RECORD
