Metadata-Version: 2.1
Name: vhpc-toolkit
Version: 1.0.3
Summary: Deploy and manage virtualized clusters for High Performance Computing (HPC) and machine learning environments on VMware software stacks
Project-URL: Homepage, https://github.com/vmware/vhpc-toolkit
Project-URL: Bug Tracker, https://github.com/vmware/vhpc-toolkit/issues
Author-email: VMware OCTO HPC/ML Group <vhpc-toolkit@vmware.com>
License-File: LICENSE.txt
Classifier: License :: OSI Approved :: MIT License
Classifier: Operating System :: OS Independent
Classifier: Programming Language :: Python :: 3
Requires-Python: >=3.7
